validar_modelos/__init__.py
validar_modelos/validar_modelos.py
validar_modelos-0.0.7.dist-info/LICENSE.txt
validar_modelos-0.0.7.dist-info/METADATA
validar_modelos-0.0.7.dist-info/WHEEL
validar_modelos-0.0.7.dist-info/top_level.txt
validar_modelos-0.0.7.dist-info/RECORD
